sdk/__init__.py
sdk/sdk.py
APIWinkSDK-0.1.1.dist-info/METADATA
APIWinkSDK-0.1.1.dist-info/WHEEL
APIWinkSDK-0.1.1.dist-info/top_level.txt
APIWinkSDK-0.1.1.dist-info/RECORD
