Metadata-Version: 2.1
Name: APIWinkSDK
Version: 0.1.1
Summary: SDK for APIWink Service to register, use and refill API request count
Home-page: https://github.com/yourusername/APIWinkSDK
Author: Your Name
Author-email: your.email@example.com
License: UNKNOWN
Platform: UNKNOWN
Classifier: Programming Language :: Python :: 3
Classifier: License :: OSI Approved :: MIT License
Classifier: Operating System :: OS Independent
Requires-Python: >=3.6
